ahh/__init__.py
ahh/era.py
ahh/exp.py
ahh/ext.py
ahh/pre.py
ahh/sci.py
ahh/vis.py
ahh/data/air.sig995.1948.nc
ahh/data/cmi.csv
ahh/data/heart_pivot.csv
ahh/data/jd_cal.pkl
ahh/data/jd_cal_leap.pkl
ahh/data/ncl_cmaps.pkl
ahh/data/rhum.sig995.1948.nc
ahh/data/slp.nc
ahh/data/steps_pivot.csv
ahh-1.0.3.dist-info/DESCRIPTION.rst
ahh-1.0.3.dist-info/METADATA
ahh-1.0.3.dist-info/RECORD
ahh-1.0.3.dist-info/WHEEL
ahh-1.0.3.dist-info/metadata.json
ahh-1.0.3.dist-info/top_level.txt
builder/__init__.py
builder/conf.py
builder/gen.py
